fred/__init__.py
fred/fred.py
fred_api_wrapper-0.0.1.dist-info/LICENSE
fred_api_wrapper-0.0.1.dist-info/METADATA
fred_api_wrapper-0.0.1.dist-info/WHEEL
fred_api_wrapper-0.0.1.dist-info/top_level.txt
fred_api_wrapper-0.0.1.dist-info/RECORD
