Metadata-Version: 2.1
Name: fred-api-wrapper
Version: 0.0.1
Summary: Wrapper to FRED API
Home-page: https://github.com/topchinesefamilysuccession/fred-api-wrapper
Author: Jorge Lameira
Author-email: author@example.com
License: UNKNOWN
Project-URL: Bug Tracker, https://github.com/topchinesefamilysuccession/fred-api-wrapper/issues
Platform: UNKNOWN
Classifier: Programming Language :: Python :: 3
Classifier: License :: OSI Approved :: MIT License
Classifier: Operating System :: OS Independent
Requires-Python: >=3.6
License-File: LICENSE
